sshaa.py
sshaa-2.1.1.dist-info/METADATA
sshaa-2.1.1.dist-info/WHEEL
sshaa-2.1.1.dist-info/entry_points.txt
sshaa-2.1.1.dist-info/top_level.txt
sshaa-2.1.1.dist-info/RECORD
