Metadata-Version: 2.1
Name: sshaa
Version: 2.1.1
Summary: Analyze auth.log
Home-page: https://github.com/yknaka/sshaa
Author: Yuki NAKAMURA
Author-email: naka_yk@live.jp
License: UNKNOWN
Project-URL: Analyze ssh auth.log, https://github.com/yknaka/sshaa
Platform: UNKNOWN
Classifier: Programming Language :: Python :: 3
Classifier: License :: OSI Approved :: MIT License
Classifier: Operating System :: OS Independent
Requires-Python: >=3.6
Requires-Dist: pandas
Requires-Dist: consoleoptions (>=1.1.0)
Requires-Dist: circlify
Requires-Dist: matplotlib
Requires-Dist: python-dateutil
